__init__.py
stty.py
tests.py
stty-0.0.5.dist-info/licenses/LICENSE
stty-0.0.5.dist-info/METADATA
stty-0.0.5.dist-info/WHEEL
stty-0.0.5.dist-info/top_level.txt
stty-0.0.5.dist-info/RECORD
