Metadata-Version: 2.4
Name: stty
Version: 0.0.5
Summary: A Python library for manipulating terminal settings in the style of POSIX stty(1).
Author-email: Soumendra Ganguly <soumendraganguly@gmail.com>
Maintainer-email: Soumendra Ganguly <soumendraganguly@gmail.com>
License: # Copyright (C) 2025 Soumendra Ganguly
Project-URL: Homepage, https://github.com/8vasu/stty.py
Project-URL: Issues, https://github.com/8vasu/stty.py/issues
Keywords: terminal,tty,stty,termios,winsize,posix,terminal-settings,pseudo-terminal,pty,terminal-attributes
Classifier: Development Status :: 4 - Beta
Classifier: Intended Audience :: Developers
Classifier: Topic :: Terminals
Classifier: Topic :: Software Development :: Libraries :: Python Modules
Classifier: Topic :: System :: Operating System
Classifier: License :: OSI Approved :: GNU General Public License v3 or later (GPLv3+)
Classifier: Programming Language :: Python :: 3
Classifier: Programming Language :: Python :: 3.13
Classifier: Programming Language :: Python :: 3 :: Only
Requires-Python: >=3.13
License-File: LICENSE
Dynamic: license-file
